cnab240/__init__.py
cnab240/errors.py
cnab240/registro.py
cnab240/tipos.py
cnab240/bancos/__init__.py
cnab240/bancos/banco_brasil/__init__.py
cnab240/bancos/banco_brasil/specs/header_arquivo.json
cnab240/bancos/banco_brasil/specs/header_lote_cobranca.json
cnab240/bancos/banco_brasil/specs/segmento_p.json
cnab240/bancos/banco_brasil/specs/segmento_q.json
cnab240/bancos/banco_brasil/specs/segmento_r.json
cnab240/bancos/banco_brasil/specs/segmento_s.json
cnab240/bancos/banco_brasil/specs/segmento_t.json
cnab240/bancos/banco_brasil/specs/segmento_u.json
cnab240/bancos/banco_brasil/specs/trailer_arquivo.json
cnab240/bancos/banco_brasil/specs/trailer_lote_cobranca.json
cnab240/bancos/bradesco/__init__.py
cnab240/bancos/bradesco/specs/header_arquivo.json
cnab240/bancos/bradesco/specs/header_lote_cobranca.json
cnab240/bancos/bradesco/specs/header_lote_extrato.json
cnab240/bancos/bradesco/specs/segmento_e.json
cnab240/bancos/bradesco/specs/segmento_p.json
cnab240/bancos/bradesco/specs/segmento_q.json
cnab240/bancos/bradesco/specs/segmento_r.json
cnab240/bancos/bradesco/specs/segmento_t.json
cnab240/bancos/bradesco/specs/segmento_u.json
cnab240/bancos/bradesco/specs/trailer_arquivo.json
cnab240/bancos/bradesco/specs/trailer_lote_cobranca.json
cnab240/bancos/bradesco/specs/trailer_lote_extrato.json
cnab240/bancos/cecred/__init__.py
cnab240/bancos/cecred/specs/header_arquivo.json
cnab240/bancos/cecred/specs/header_lote_cobranca.json
cnab240/bancos/cecred/specs/segmento_p.json
cnab240/bancos/cecred/specs/segmento_q.json
cnab240/bancos/cecred/specs/segmento_r.json
cnab240/bancos/cecred/specs/segmento_s.json
cnab240/bancos/cecred/specs/segmento_t.json
cnab240/bancos/cecred/specs/segmento_u.json
cnab240/bancos/cecred/specs/trailer_arquivo.json
cnab240/bancos/cecred/specs/trailer_lote_cobranca.json
cnab240/bancos/cef/__init__.py
cnab240/bancos/cef/specs/header_arquivo.json
cnab240/bancos/cef/specs/header_lote_cobranca.json
cnab240/bancos/cef/specs/segmento_p.json
python3_cnab-1.0.11.dist-info/LICENSE.md
python3_cnab-1.0.11.dist-info/METADATA
python3_cnab-1.0.11.dist-info/WHEEL
python3_cnab-1.0.11.dist-info/top_level.txt
python3_cnab-1.0.11.dist-info/RECORD
