Metadata-Version: 2.1
Name: python3-cnab
Version: 1.0.11
Summary: Lib para gerar arquivo CNAB - Integração bancária
Home-page: https://github.com/Trust-Code/python-cnab
Author: Trustcode
Author-email: suporte@trustcode.com.br
License: MIT
Download-URL: https://github.com/Trust-Code/python-cnab
Keywords: cnab,cnab240
Platform: any
Classifier: Development Status :: 3 - Alpha
Classifier: Environment :: Plugins
Classifier: Intended Audience :: Developers
Classifier: Operating System :: OS Independent
Classifier: Programming Language :: Python
Classifier: Programming Language :: Python :: 3.6
Classifier: Programming Language :: Python :: 3.5
Classifier: Programming Language :: Python :: 3.4
Classifier: Topic :: Software Development :: Libraries :: Python Modules
Requires-Dist: setuptools-git (==1.1)
